delfino_core/__init__.py
delfino_core/backports.py
delfino_core/changelog_urls.yaml
delfino_core/commands/__init__.py
delfino_core/commands/dependencies_update.py
delfino_core/commands/issue_tracker.py
delfino_core/commands/pre_commit.py
delfino_core/commands/ruff.py
delfino_core/commands/switch_python_version.py
delfino_core/commands/test.py
delfino_core/commands/typecheck.py
delfino_core/commands/vcs.py
delfino_core/commands/verify.py
delfino_core/config.py
delfino_core/spinner.py
delfino_core/utils.py
delfino_core/vcs_tools.py
delfino_core-10.0.1.dist-info/WHEEL
delfino_core-10.0.1.dist-info/entry_points.txt
delfino_core-10.0.1.dist-info/METADATA
delfino_core-10.0.1.dist-info/RECORD
