Metadata-Version: 2.3
Name: delfino-core
Version: 10.0.1
Summary: Delfino core plugin
Author: Radek Lát
Author-email: Radek Lát <radek.lat@gmail.com>
License: MIT License
Classifier: Development Status :: 4 - Beta
Classifier: Environment :: Console
Classifier: Intended Audience :: Developers
Classifier: License :: OSI Approved :: MIT License
Classifier: Operating System :: OS Independent
Classifier: Programming Language :: Python :: 3
Classifier: Programming Language :: Python :: 3 :: Only
Classifier: Programming Language :: Python :: 3.9
Classifier: Programming Language :: Python :: 3.10
Classifier: Programming Language :: Python :: 3.11
Classifier: Programming Language :: Python :: 3.12
Classifier: Programming Language :: Python :: 3.13
Classifier: Topic :: Software Development
Classifier: Topic :: Utilities
Requires-Dist: delfino>=5.0.1
Requires-Dist: pre-commit ; extra == 'all'
Requires-Dist: pytest ; extra == 'all'
Requires-Dist: coverage ; extra == 'all'
Requires-Dist: pytest-cov ; extra == 'all'
Requires-Dist: mypy ; extra == 'all'
Requires-Dist: gitpython ; extra == 'all'
Requires-Dist: pyyaml ; extra == 'all'
Requires-Dist: ruff>=0.5.0 ; extra == 'all'
Requires-Dist: httpx ; extra == 'all'
Requires-Dist: gitpython ; extra == 'dependencies-update'
Requires-Dist: mypy ; extra == 'mypy'
Requires-Dist: pyyaml ; extra == 'pre-commit'
Requires-Dist: ruff>=0.5.0 ; extra == 'ruff'
Requires-Dist: pytest ; extra == 'test'
Requires-Dist: coverage ; extra == 'test'
Requires-Dist: pytest-cov ; extra == 'test'
Requires-Dist: httpx ; extra == 'vcs'
Requires-Dist: pre-commit ; extra == 'verify'
Requires-Dist: pytest ; extra == 'verify'
Requires-Dist: coverage ; extra == 'verify'
Requires-Dist: pytest-cov ; extra == 'verify'
Requires-Dist: mypy ; extra == 'verify'
Requires-Dist: ruff>=0.5.0 ; extra == 'verify'
Requires-Python: >=3.10.0
Provides-Extra: all
Provides-Extra: dependencies-update
Provides-Extra: mypy
Provides-Extra: pre-commit
Provides-Extra: ruff
Provides-Extra: test
Provides-Extra: vcs
Provides-Extra: verify
